coder/__init__.py
coder/core.py
coder/utils.py
coder_api-0.1.14.dist-info/licenses/LICENSE.txt
tests/__init__.py
tests/test_core.py
coder_api-0.1.14.dist-info/METADATA
coder_api-0.1.14.dist-info/WHEEL
coder_api-0.1.14.dist-info/top_level.txt
coder_api-0.1.14.dist-info/RECORD
