Metadata-Version: 2.4
Name: coder-api
Version: 0.1.14
Summary: Python bindings for the Coder API
Home-page: https://gitlab.smartflow.me/coder/api-coder
Author: Lucas Tarsitano Garcia
Author-email: lucas.garcia@smartflowsistemas.com.br
Maintainer: Nathan Daniel Breier
Maintainer-email: nathan.breier@smartflowsistemas.com.br
License: LGPLv3
Classifier: Development Status :: 1 - Planning
Classifier: Programming Language :: Python :: 3
Classifier: Intended Audience :: Developers
Classifier: License :: OSI Approved :: GNU Lesser General Public License v3 (LGPLv3)
Classifier: Operating System :: OS Independent
Classifier: Topic :: Software Development
Classifier: Topic :: Software Development :: Libraries
Classifier: Topic :: Software Development :: Libraries :: Python Modules
Requires-Python: >=3.6
License-File: LICENSE.txt
Requires-Dist: requests
Dynamic: author
Dynamic: author-email
Dynamic: classifier
Dynamic: description
Dynamic: description-content-type
Dynamic: home-page
Dynamic: license
Dynamic: license-file
Dynamic: maintainer
Dynamic: maintainer-email
Dynamic: requires-dist
Dynamic: requires-python
Dynamic: summary
